safeshell/__init__.py
safeshell/core.py
safeshell/errors.py
safeshell/networking.py
safeshell/py.typed
safeshell/types.py
safeshell/integrations/__init__.py
safeshell/integrations/langchain.py
safeshell/integrations/pydantic_ai.py
safeshell/sandbox/__init__.py
safeshell/sandbox/landlock.py
safeshell/sandbox/native.py
safeshell/sandbox/seatbelt.py
safeshell-1.0.1.dist-info/METADATA
safeshell-1.0.1.dist-info/WHEEL
safeshell-1.0.1.dist-info/licenses/LICENSE
safeshell-1.0.1.dist-info/RECORD
